<?xml version="1.0" encoding="utf-8"?>
<items>
<item><title>January Is a MAJOR Month for New Hair-Care Products</title><url_post>https://www.allure.com/gallery/best-hair-care-product-launches-january-2019</url_post><url_img></url_img><date>January 29, 2019</date><categ></categ><site></site><tags></tags><description></description></item>
<item><title>Here Are the Beauty Products </title><url_post>https://www.allure.com/gallery/editors-favorite-new-beauty-products</url_post><url_img></url_img><date>January 28, 2019</date><categ></categ><site></site><tags></tags><description></description></item>
<item><title>7 Green Beauty Trends We Predict Will Be Big This Year</title><url_post>https://www.allure.com/gallery/green-beauty-trends-2019</url_post><url_img></url_img><date>January 28, 2019</date><categ></categ><site></site><tags></tags><description></description></item>
<item><title>The 31 Most Exciting Beauty Products to Try in 2019</title><url_post>https://www.allure.com/gallery/must-try-beauty-products-bucket-list</url_post><url_img></url_img><date>January 25, 2019</date><categ></categ><site></site><tags></tags><description></description></item>
<item><title>The 16 Best Makeup, Hair, and Skin Products Under $10</title><url_post>https://www.allure.com/gallery/best-cheap-makeup-beauty-products-under-10</url_post><url_img></url_img><date>January 24, 2019</date><categ></categ><site></site><tags></tags><description></description></item>
<item><title>The 35 Best Drugstore Beauty Products Launching in 2019</title><url_post>https://www.allure.com/gallery/best-new-drugstore-beauty-launches</url_post><url_img></url_img><date>January 22, 2019</date><categ></categ><site></site><tags></tags><description></description></item>
<item><title>Your Guide to Meghan Markle's Favorite Beauty Products and Fashion Brands</title><url_post>https://www.allure.com/gallery/meghan-markle-beauty-products-favorite-clothes</url_post><url_img></url_img><date>January 17, 2019</date><categ></categ><site></site><tags></tags><description></description></item>
<item><title>All Of Sephora's January 2019 Sales &amp; Beauty Insider Rewards</title><url_post>https://www.allure.com/story/sephora-january-2019-monthly-sales-deals-rewards-for-vibs</url_post><url_img></url_img><date>January 15, 2019</date><categ></categ><site></site><tags></tags><description></description></item>
<item><title>The Luxury Beauty Products That Are Actually Worth It</title><url_post>https://www.allure.com/gallery/best-luxury-beauty-products-makeup-worth-the-money</url_post><url_img></url_img><date>January 12, 2019</date><categ></categ><site></site><tags></tags><description></description></item>
<item><title>Where to Donate Your Unused or Gently Used Beauty Products</title><url_post>https://www.allure.com/story/where-to-donate-makeup-beauty-products-used-unused</url_post><url_img></url_img><date>January 5, 2019</date><categ></categ><site></site><tags></tags><description></description></item>
<item><title>Your Favorite Indie Hair-Care Brand Just Dropped a Blow Dryer</title><url_post>https://www.allure.com/story/its-a-10-haircare-miracle-professional-hair-dryer</url_post><url_img></url_img><date>January 5, 2019</date><categ></categ><site></site><tags></tags><description></description></item>
<item><title>Kristin Ess Just Dropped an Entire Hair-Care Collection for Your Scalp</title><url_post>https://www.allure.com/story/kristin-ess-scalp-hair-care-collection</url_post><url_img></url_img><date>January 4, 2019</date><categ></categ><site></site><tags></tags><description></description></item>
<item><title>The 13 Best Beauty Products You Can Buy on Amazon</title><url_post>https://www.allure.com/gallery/best-beauty-products-amazon</url_post><url_img></url_img><date>January 3, 2019</date><categ></categ><site></site><tags></tags><description></description></item>
<item><title>Kick Off 2019 With This Huge Beauty Sale on All Your Favorite Brands</title><url_post>https://www.allure.com/story/dermstore-new-year-sale-beauty-deals</url_post><url_img></url_img><date>January 1, 2019</date><categ></categ><site></site><tags></tags><description></description></item>
<item><title>The Best New Makeup Launching in January</title><url_post>https://www.allure.com/gallery/new-makeup-launches-january-2019</url_post><url_img></url_img><date>January 1, 2019</date><categ></categ><site></site><tags></tags><description></description></item>
<item><title> Editors' Favorite Beauty Products of December 2018</title><url_post>https://www.allure.com/gallery/best-new-beauty-products-december-2018</url_post><url_img></url_img><date>December 31, 2018</date><categ></categ><site></site><tags></tags><description></description></item>
<item><title>The Best After-Holiday Beauty Sales to Shop Before the End of the Year</title><url_post>https://www.allure.com/story/after-christmas-beauty-sales-end-of-year-deals</url_post><url_img></url_img><date>December 29, 2018</date><categ></categ><site></site><tags></tags><description></description></item>
<item><title>IGK's New Shine-Enhancing Hair Oil Blings Out All Hair Types</title><url_post>https://www.allure.com/gallery/best-new-hair-products-december-2018</url_post><url_img></url_img><date>December 21, 2018</date><categ></categ><site></site><tags></tags><description></description></item>
<item><title>Anthropologie Is Having a Major Sale on Beauty Products</title><url_post>https://www.allure.com/story/anthropologie-30-percent-off-sale-beauty-products</url_post><url_img></url_img><date>December 15, 2018</date><categ></categ><site></site><tags></tags><description></description></item>
<item><title>The Most-Searched Beauty Brand of 2018 Is Actually Really Surprising</title><url_post>https://www.allure.com/story/most-searched-beauty-brand-2018</url_post><url_img></url_img><date>December 14, 2018</date><categ></categ><site></site><tags></tags><description></description></item>
</items><?xml version="1.0" encoding="utf-8"?>
<items>
<item><title>January Is a MAJOR Month for New Hair-Care Products</title><url_post>https://www.allure.com/gallery/best-hair-care-product-launches-january-2019</url_post><url_img></url_img><date>January 29, 2019</date><categ>news</categ><site>www.allure.com</site><tags>#allure@beautybus #красота@beautybus #allure #красота</tags><description></description></item>
<item><title>Here Are the Beauty Products </title><url_post>https://www.allure.com/gallery/editors-favorite-new-beauty-products</url_post><url_img></url_img><date>January 28, 2019</date><categ>news</categ><site>www.allure.com</site><tags>#allure@beautybus #красота@beautybus #allure #красота</tags><description></description></item>
<item><title>7 Green Beauty Trends We Predict Will Be Big This Year</title><url_post>https://www.allure.com/gallery/green-beauty-trends-2019</url_post><url_img></url_img><date>January 28, 2019</date><categ>news</categ><site>www.allure.com</site><tags>#allure@beautybus #красота@beautybus #allure #красота</tags><description></description></item>
<item><title>The 31 Most Exciting Beauty Products to Try in 2019</title><url_post>https://www.allure.com/gallery/must-try-beauty-products-bucket-list</url_post><url_img></url_img><date>January 25, 2019</date><categ>news</categ><site>www.allure.com</site><tags>#allure@beautybus #красота@beautybus #allure #красота</tags><description></description></item>
<item><title>The 16 Best Makeup, Hair, and Skin Products Under $10</title><url_post>https://www.allure.com/gallery/best-cheap-makeup-beauty-products-under-10</url_post><url_img></url_img><date>January 24, 2019</date><categ>news</categ><site>www.allure.com</site><tags>#allure@beautybus #красота@beautybus #allure #красота</tags><description></description></item>
<item><title>The 35 Best Drugstore Beauty Products Launching in 2019</title><url_post>https://www.allure.com/gallery/best-new-drugstore-beauty-launches</url_post><url_img></url_img><date>January 22, 2019</date><categ>news</categ><site>www.allure.com</site><tags>#allure@beautybus #красота@beautybus #allure #красота</tags><description></description></item>
<item><title>Your Guide to Meghan Markle's Favorite Beauty Products and Fashion Brands</title><url_post>https://www.allure.com/gallery/meghan-markle-beauty-products-favorite-clothes</url_post><url_img></url_img><date>January 17, 2019</date><categ>news</categ><site>www.allure.com</site><tags>#allure@beautybus #красота@beautybus #allure #красота</tags><description></description></item>
<item><title>All Of Sephora's January 2019 Sales &amp; Beauty Insider Rewards</title><url_post>https://www.allure.com/story/sephora-january-2019-monthly-sales-deals-rewards-for-vibs</url_post><url_img></url_img><date>January 15, 2019</date><categ>news</categ><site>www.allure.com</site><tags>#allure@beautybus #красота@beautybus #allure #красота</tags><description></description></item>
<item><title>The Luxury Beauty Products That Are Actually Worth It</title><url_post>https://www.allure.com/gallery/best-luxury-beauty-products-makeup-worth-the-money</url_post><url_img></url_img><date>January 12, 2019</date><categ>news</categ><site>www.allure.com</site><tags>#allure@beautybus #красота@beautybus #allure #красота</tags><description></description></item>
<item><title>Where to Donate Your Unused or Gently Used Beauty Products</title><url_post>https://www.allure.com/story/where-to-donate-makeup-beauty-products-used-unused</url_post><url_img></url_img><date>January 5, 2019</date><categ>news</categ><site>www.allure.com</site><tags>#allure@beautybus #красота@beautybus #allure #красота</tags><description></description></item>
<item><title>Your Favorite Indie Hair-Care Brand Just Dropped a Blow Dryer</title><url_post>https://www.allure.com/story/its-a-10-haircare-miracle-professional-hair-dryer</url_post><url_img></url_img><date>January 5, 2019</date><categ>news</categ><site>www.allure.com</site><tags>#allure@beautybus #красота@beautybus #allure #красота</tags><description></description></item>
<item><title>Kristin Ess Just Dropped an Entire Hair-Care Collection for Your Scalp</title><url_post>https://www.allure.com/story/kristin-ess-scalp-hair-care-collection</url_post><url_img></url_img><date>January 4, 2019</date><categ>news</categ><site>www.allure.com</site><tags>#allure@beautybus #красота@beautybus #allure #красота</tags><description></description></item>
<item><title>The 13 Best Beauty Products You Can Buy on Amazon</title><url_post>https://www.allure.com/gallery/best-beauty-products-amazon</url_post><url_img></url_img><date>January 3, 2019</date><categ>news</categ><site>www.allure.com</site><tags>#allure@beautybus #красота@beautybus #allure #красота</tags><description></description></item>
<item><title>Kick Off 2019 With This Huge Beauty Sale on All Your Favorite Brands</title><url_post>https://www.allure.com/story/dermstore-new-year-sale-beauty-deals</url_post><url_img></url_img><date>January 1, 2019</date><categ>news</categ><site>www.allure.com</site><tags>#allure@beautybus #красота@beautybus #allure #красота</tags><description></description></item>
<item><title>The Best New Makeup Launching in January</title><url_post>https://www.allure.com/gallery/new-makeup-launches-january-2019</url_post><url_img></url_img><date>January 1, 2019</date><categ>news</categ><site>www.allure.com</site><tags>#allure@beautybus #красота@beautybus #allure #красота</tags><description></description></item>
<item><title> Editors' Favorite Beauty Products of December 2018</title><url_post>https://www.allure.com/gallery/best-new-beauty-products-december-2018</url_post><url_img></url_img><date>December 31, 2018</date><categ>news</categ><site>www.allure.com</site><tags>#allure@beautybus #красота@beautybus #allure #красота</tags><description></description></item>
<item><title>The Best After-Holiday Beauty Sales to Shop Before the End of the Year</title><url_post>https://www.allure.com/story/after-christmas-beauty-sales-end-of-year-deals</url_post><url_img></url_img><date>December 29, 2018</date><categ>news</categ><site>www.allure.com</site><tags>#allure@beautybus #красота@beautybus #allure #красота</tags><description></description></item>
<item><title>IGK's New Shine-Enhancing Hair Oil Blings Out All Hair Types</title><url_post>https://www.allure.com/gallery/best-new-hair-products-december-2018</url_post><url_img></url_img><date>December 21, 2018</date><categ>news</categ><site>www.allure.com</site><tags>#allure@beautybus #красота@beautybus #allure #красота</tags><description></description></item>
<item><title>Anthropologie Is Having a Major Sale on Beauty Products</title><url_post>https://www.allure.com/story/anthropologie-30-percent-off-sale-beauty-products</url_post><url_img></url_img><date>December 15, 2018</date><categ>news</categ><site>www.allure.com</site><tags>#allure@beautybus #красота@beautybus #allure #красота</tags><description></description></item>
<item><title>The Most-Searched Beauty Brand of 2018 Is Actually Really Surprising</title><url_post>https://www.allure.com/story/most-searched-beauty-brand-2018</url_post><url_img></url_img><date>December 14, 2018</date><categ>news</categ><site>www.allure.com</site><tags>#allure@beautybus #красота@beautybus #allure #красота</tags><description></description></item>
</items>